{
  "type": "FeatureCollection",
  "features": [
    {
      "type": "Feature",
      "properties": {},
      "geometry": {
        "coordinates": [
          [
            [
              -122.83822104341611,
              49.010955198516285
            ],
            [
              -124.52343309829531,
              47.865479497616235
            ],
            [
              -124.45339616154078,
              46.19484140647796
            ],
            [
              -124.38335922478556,
              44.87028133452327
            ],
            [
              -124.31332228803035,
              43.41285487943341
            ],
            [
              -124.03317454101014,
              41.02742232349374
            ],
            [
              -124.45339616154078,
              39.96224794514356
            ],
            [
              -123.96313760425494,
              38.825675601640995
            ],
            [
              -122.91258355292936,
              37.55970897240714
            ],
            [
              -121.65191869133812,
              36.045674714517574
            ],
            [
              -120.18114301948191,
              34.790044352552215
            ],
            [
              -118.50025653736071,
              33.515001493965954
            ],
            [
              -116.53922230821868,
              32.63469695335651
            ],
            [
              -114.08792952179144,
              32.22088705953098
            ],
            [
              -112.26696916615981,
              31.62645097199278
            ],
            [
              -109.0452700754272,
              31.56679646887872
            ],
            [
              -106.52394035224542,
              31.38760400916145
            ],
            [
              -105.33331242740941,
              30.787827955146426
            ],
            [
              -104.84305387012357,
              30.002497840601976
            ],
            [
              -103.16216738800236,
              28.96609053478754
            ],
            [
              -102.32172414694178,
              29.759592785480166
            ],
            [
              -100.99102234859532,
              28.659259273374772
            ],
            [
              -100.15057910753472,
              27.298586505167947
            ],
            [
              -99.59028361349432,
              26.235563598644035
            ],
            [
              -96.99891695355667,
              26.17272461230894
            ],
            [
              -97.2090277638223,
              27.174043152599594
            ],
            [
              -96.22851064925129,
              28.166458370266454
            ],
            [
              -94.89780887370767,
              28.904797248485863
            ],
            [
              -93.49707013860602,
              29.455132406022344
            ],
            [
              -89.6450386170778,
              30.426153270431413
            ],
            [
              -86.00311790581523,
              30.184288134311814
            ],
            [
              -83.20164043561259,
              29.027348771128786
            ],
            [
              -83.27167737236782,
              28.1046980246834
            ],
            [
              -82.361197194552,
              26.549248814062594
            ],
            [
              -80.8904215226958,
              24.718193409719404
            ],
            [
              -79.90990440812477,
              25.73190666101901
            ],
            [
              -80.04997828163454,
              27.671378088035297
            ],
            [
              -80.61027377567561,
              29.69877479006621
            ],
            [
              -81.2406067962285,
              30.847976740062762
            ],
            [
              -80.68031162151729,
              31.864687633467398
            ],
            [
              -79.27957288641565,
              33.16393849301129
            ],
            [
              -77.17846478376417,
              34.212867707514846
            ],
            [
              -75.21743055462245,
              35.76202617547351
            ],
            [
              -75.63765217515275,
              36.94649680027072
            ],
            [
              -75.56761523839754,
              38.22296045264807
            ],
            [
              -74.72717199733749,
              39.930068691398276
            ],
            [
              -73.95676585266543,
              40.73091536241665
            ],
            [
              -72.90621180133954,
              41.10138687942609
            ],
            [
              -70.03469739438198,
              41.992445082028325
            ],
            [
              -70.45491901491228,
              42.614023011952725
            ],
            [
              -69.26429109007628,
              43.33143322586034
            ],
            [
              -67.02310911391436,
              44.29166327589223
            ],
            [
              -67.44332841473096,
              45.03882920605483
            ],
            [
              -67.44332841473086,
              45.76652067582344
            ],
            [
              -67.66071574714938,
              47.24790487214031
            ],
            [
              -69.13149250309797,
              46.91405775848375
            ],
            [
              -69.8318618706488,
              46.33687910603453
            ],
            [
              -71.72285916303562,
              45.311998083679526
            ],
            [
              -73.47378258191202,
              45.311998083679526
            ],
            [
              -75.08463337955276,
              44.817325715221614
            ],
            [
              -75.36478112657295,
              44.46850838889003
            ],
            [
              -76.13518743087832,
              43.511149438488815
            ],
            [
              -76.69548292491871,
              43.46033444865631
            ],
            [
              -77.88611084975469,
              43.511149438488815
            ],
            [
              -78.58648021730555,
              43.256647092641714
            ],
            [
              -79.56699733187659,
              42.79585153667381
            ],
            [
              -81.09841953652246,
              42.39491255976134
            ],
            [
              -82.5691959001263,
              42.2395506407193
            ],
            [
              -83.05945445741217,
              42.60146473666512
            ],
            [
              -82.8493436471465,
              43.21702506821029
            ],
            [
              -83.05945445741217,
              43.82643355374637
            ],
            [
              -83.17745232687327,
              45.24265871989701
            ],
            [
              -84.43811715086362,
              45.63579633295896
            ],
            [
              -86.11900363298483,
              44.597967407217084
            ],
            [
              -86.32911471975203,
              43.7945718795589
            ],
            [
              -86.32911471975203,
              43.13375124475314
            ],
            [
              -87.16955796081263,
              41.99900156558411
            ],
            [
              -87.4497058667289,
              42.877666727455164
            ],
            [
              -87.4497058667293,
              44.46193543322215
            ],
            [
              -87.16955789382588,
              45.35475807071529
            ],
            [
              -86.46918852627505,
              45.990949884627696
            ],
            [
              -82.99562403804623,
              45.92175413565403
            ],
            [
              -83.48588106746753,
              46.406821111343476
            ],
            [
              -84.74654592905809,
              46.98325756065742
            ],
            [
              -86.11551878589498,
              46.852813076727216
            ],
            [
              -88.21662693982186,
              46.852813036942166
            ],
            [
              -90.66791972624911,
              46.804895176346434
            ],
            [
              -92.27876927161508,
              46.94852061421497
            ],
            [
              -90.66791972624911,
              47.377091321128205
            ],
            [
              -90.10762423220872,
              48.13046621140961
            ],
            [
              -92.83906476565613,
              48.68834751806165
            ],
            [
              -95.36039448883788,
              49.056871406076766
            ],
            [
              -101.03338636599773,
              49.14857841671869
            ],
            [
              -107.5701671298032,
              49.14857841671753
            ],
            [
              -113.80345620201393,
              49.148579273045385
            ],
            [
              -119.12626339539833,
              49.19436923618903
            ],
            [
              -122.83822104341611,
              49.010955198516285
            ]
          ]
        ],
        "type": "Polygon"
      }
    }
  ]
}